newsletter/__init__.py
newsletter/admin.py
newsletter/apps.py
newsletter/forms.py
newsletter/models.py
newsletter/tests.py
newsletter/urls.py
newsletter/views.py
newsletter/migrations/0001_initial.py
newsletter/migrations/__init__.py
newsletter/templates/newsletter/news_letter.html
django_manage_newsletter-0.0.2.dist-info/LICENSE
django_manage_newsletter-0.0.2.dist-info/METADATA
django_manage_newsletter-0.0.2.dist-info/WHEEL
django_manage_newsletter-0.0.2.dist-info/top_level.txt
django_manage_newsletter-0.0.2.dist-info/RECORD
