Metadata-Version: 2.1
Name: django-manage-newsletter
Version: 0.0.2
Summary: A Django app to manage newsletter subscriptions
Home-page: https://github.com/bobby-didcoding/django-manage-newsletter
Author: Bobby Stearman
Author-email: bobby@didcoding.com
License: UNKNOWN
Project-URL: Bug Tracker, https://github.com/bobby-didcoding/django-manage-newsletter/issues
Platform: UNKNOWN
Classifier: Programming Language :: Python :: 3
Classifier: License :: OSI Approved :: BSD License
Classifier: Operating System :: OS Independent
Requires-Python: >=3.6
Requires-Dist: Django (>=3.2)
